{
  "timestamp": "2026-03-06T03:35:24.940942",
  "immediate_actions": [
    {
      "action": "部署 Dify 环境",
      "priority": "high",
      "command": "cd dify/docker && docker compose up -d",
      "expected_time": "5分钟"
    },
    {
      "action": "创建第一个智能体",
      "priority": "high",
      "command": "访问 http://localhost/install",
      "expected_time": "10分钟"
    },
    {
      "action": "运行自主化学习系统",
      "priority": "high",
      "command": "python scripts/autonomous-learning.py",
      "expected_time": "2分钟"
    },
    {
      "action": "启动几何增长系统",
      "priority": "high",
      "command": "python scripts/geometric-growth.py",
      "expected_time": "2分钟"
    },
    {
      "action": "缩短学习周期",
      "priority": "high",
      "command": "python scripts/learning-cycle-shortener.py",
      "expected_time": "2分钟"
    }
  ],
  "execution_order": [
    "部署 Dify 环境",
    "创建第一个智能体",
    "运行自主化学习系统",
    "启动几何增长系统",
    "缩短学习周期"
  ],
  "success_criteria": [
    "Dify 成功运行",
    "智能体创建完成",
    "学习系统启动",
    "增长策略制定",
    "周期缩短实现"
  ]
}